aiomrim/__init__.py
aiomrim/__main__.py
aiomrim/account.py
aiomrim/admin.py
aiomrim/check_connection.py
aiomrim/exceptions.py
aiomrim/online.py
aiomrim/welcome.py
aiomrim-1.1.dist-info/licenses/LICENSE
aiomrim-1.1.dist-info/METADATA
aiomrim-1.1.dist-info/WHEEL
aiomrim-1.1.dist-info/entry_points.txt
aiomrim-1.1.dist-info/top_level.txt
aiomrim-1.1.dist-info/RECORD
