Metadata-Version: 2.4
Name: aiomrim
Version: 1.1
Summary: Awesome SDK for Async Operations with MRIM-Server (https://github.com/mrimsu/mrim-server)
Home-page: https://github.com/fayzetwin1/aiomrim
Author: fayzetwin
Author-email: contact@fayzetwin.xyz
License-File: LICENSE
Requires-Dist: aiohttp>=3.12.0
Requires-Dist: asyncio>=3.4.3
Dynamic: author
Dynamic: author-email
Dynamic: home-page
Dynamic: license-file
Dynamic: requires-dist
Dynamic: summary
